catalax/__init__.py
catalax/objectives.py
catalax/predictor.py
catalax/surrogate.py
catalax/widget.py
catalax/dataset/__init__.py
catalax/dataset/croissant.py
catalax/dataset/dataset.py
catalax/dataset/enzymeml.py
catalax/dataset/measurement.py
catalax/dataset/metrics.py
catalax/laws/__init__.py
catalax/laws/activation.py
catalax/laws/enzymatic.py
catalax/laws/hill_type.py
catalax/laws/inhibition.py
catalax/laws/mass_action.py
catalax/mcmc/__init__.py
catalax/mcmc/mcmc.py
catalax/mcmc/plotting.py
catalax/mcmc/priors.py
catalax/mcmc/protocols.py
catalax/mcmc/results.py
catalax/mcmc/models/__init__.py
catalax/mcmc/models/init_estimator.py
catalax/model/__init__.py
catalax/model/assignment.py
catalax/model/base.py
catalax/model/constant.py
catalax/model/enzymeml.py
catalax/model/equation.py
catalax/model/inaxes.py
catalax/model/model.py
catalax/model/ode.py
catalax/model/parameter.py
catalax/model/reaction.py
catalax/model/simconfig.py
catalax/model/state.py
catalax/model/stoich.py
catalax/model/types.py
catalax/model/utils.py
catalax/neural/__init__.py
catalax/neural/mlp.py
catalax/neural/neuralbase.py
catalax/neural/neuralode.py
catalax/neural/rateflow.py
catalax/neural/rbf.py
catalax/neural/strategy.py
catalax/neural/trainer.py
catalax/neural/universalode.py
catalax/neural/utils.py
catalax/neural/penalties/__init__.py
catalax/neural/penalties/penalties.py
catalax/neural/penalties/stoich_mat.py
catalax/neural/penalties/uode.py
catalax/neural/penalties/weight.py
catalax/neural/plots/__init__.py
catalax/neural/plots/phaseplot.py
catalax/neural/plots/rateflow.py
catalax/tools/__init__.py
catalax/tools/enzymeml.py
catalax/tools/optimization.py
catalax/tools/simulation.py
catalax/tools/stack.py
catalax/tools/symbolicmodule.py
catalax-0.5.4.dist-info/METADATA
catalax-0.5.4.dist-info/WHEEL
catalax-0.5.4.dist-info/RECORD
