Metadata-Version: 2.4
Name: catalax
Version: 0.5.4
Summary: A JAX-based framework for (neural) ODE modelling in biocatalysis.
Author-email: Jan Range <jan.range@simtech.uni-stuttgart.de>
License-Expression: MIT
Requires-Python: <3.15,>=3.11
Requires-Dist: arviz<0.30.0,>=0.22.0
Requires-Dist: corner<3,>=2.2.2
Requires-Dist: deprecated>=1.2.18
Requires-Dist: diffrax<0.8,>=0.7.0
Requires-Dist: dotted-dict<2,>=1.1.3
Requires-Dist: equinox<0.14,>=0.13
Requires-Dist: ipywidgets<9,>=8.1.1
Requires-Dist: jax<0.8.0,>=0.7.0
Requires-Dist: jinja2<4,>=3.1.2
Requires-Dist: lmfit<2,>=1.3.4
Requires-Dist: matplotlib<4,>=3.8.0
Requires-Dist: mlcroissant<2,>=1.0.10
Requires-Dist: numpy<3,>=2.1.0
Requires-Dist: numpyro<0.20.0,>=0.19.0
Requires-Dist: optax<0.3,>=0.2.5
Requires-Dist: pandas<3,>=2.2.3
Requires-Dist: pydantic<3,>=2.9.2
Requires-Dist: pyenzyme<3,>=2.2.1
Requires-Dist: rich<14,>=13.8.1
Requires-Dist: seaborn<0.14,>=0.13.2
Requires-Dist: sympy~=1.12
Requires-Dist: tqdm<5,>=4.66.1
Requires-Dist: typing-extensions<5,>=4.14.1
